<?xml version="1.0" encoding="UTF-8"?><!--This file was generated by the ALFA Plugin for Eclipse from Axiomatics AB (http://www.axiomatics.com).--><!--Any modification to this file will be lost upon recompilation of the source ALFA file--><xacml3:Policy xmlns:xacml3="urn:oasis:names:tc:xacml:3.0:core:schema:wd-17" PolicyId="http://axiomatics.com/alfa/identifier/AcmeCorp.Finance.PurchaseOrders" RuleCombiningAlgId="urn:oasis:names:tc:xacml:3.0:rule-combining-algorithm:permit-unless-deny" Version="1.0"><xacml3:Description/><xacml3:PolicyDefaults><xacml3:XPathVersion>http://www.w3.org/TR/1999/REC-xpath-19991116</xacml3:XPathVersion></xacml3:PolicyDefaults><xacml3:Target><xacml3:AnyOf><xacml3:AllOf><xacml3:Match MatchId="urn:oasis:names:tc:xacml:1.0:function:string-equal"><xacml3:AttributeValue DataType="http://www.w3.org/2001/XMLSchema#string">PurchaseOrder</xacml3:AttributeValue><xacml3:AttributeDesignator AttributeId="urn:oasis:names:tc:xacml:1.0:resource:Resource-type" Category="urn:oasis:names:tc:xacml:3.0:attribute-category:resource" DataType="http://www.w3.org/2001/XMLSchema#string" MustBePresent="false"/></xacml3:Match></xacml3:AllOf></xacml3:AnyOf></xacml3:Target><xacml3:Rule Effect="Deny" RuleId="AcmeCorp.Finance.PurchaseOrders.RestrictToEmployees"><xacml3:Description/><xacml3:Target/><xacml3:Condition><xacml3:Apply FunctionId="urn:oasis:names:tc:xacml:1.0:function:not"><xacml3:Apply FunctionId="urn:oasis:names:tc:xacml:3.0:function:any-of-any"><xacml3:Function FunctionId="urn:oasis:names:tc:xacml:1.0:function:string-equal"/><xacml3:AttributeDesignator AttributeId="urn:oasis:names:tc:xacml:1.0:subject:subject-role" Category="urn:oasis:names:tc:xacml:1.0:subject-category:access-subject" DataType="http://www.w3.org/2001/XMLSchema#string" MustBePresent="false"/><xacml3:AttributeValue DataType="http://www.w3.org/2001/XMLSchema#string">employee</xacml3:AttributeValue></xacml3:Apply></xacml3:Apply></xacml3:Condition></xacml3:Rule><xacml3:Rule Effect="Deny" RuleId="AcmeCorp.Finance.PurchaseOrders.RestrictCreation"><xacml3:Description/><xacml3:Target><xacml3:AnyOf><xacml3:AllOf><xacml3:Match MatchId="urn:oasis:names:tc:xacml:1.0:function:string-equal"><xacml3:AttributeValue DataType="http://www.w3.org/2001/XMLSchema#string">Create</xacml3:AttributeValue><xacml3:AttributeDesignator AttributeId="urn:oasis:names:tc:xacml:1.0:action:action" Category="urn:oasis:names:tc:xacml:3.0:attribute-category:action" DataType="http://www.w3.org/2001/XMLSchema#string" MustBePresent="false"/></xacml3:Match></xacml3:AllOf></xacml3:AnyOf></xacml3:Target><xacml3:Condition><xacml3:Apply FunctionId="urn:oasis:names:tc:xacml:1.0:function:not"><xacml3:Apply FunctionId="urn:oasis:names:tc:xacml:3.0:function:any-of-any"><xacml3:Function FunctionId="urn:oasis:names:tc:xacml:1.0:function:string-equal"/><xacml3:AttributeDesignator AttributeId="urn:oasis:names:tc:xacml:1.0:subject:subject-role" Category="urn:oasis:names:tc:xacml:1.0:subject-category:access-subject" DataType="http://www.w3.org/2001/XMLSchema#string" MustBePresent="false"/><xacml3:AttributeValue DataType="http://www.w3.org/2001/XMLSchema#string">manager</xacml3:AttributeValue></xacml3:Apply></xacml3:Apply></xacml3:Condition></xacml3:Rule></xacml3:Policy>